staryk/__init__.py
staryk/circuit.py
staryk/const.py
staryk/dimension.py
staryk/earth.py
staryk/equationMod.py
staryk/flight.py
staryk/moon.py
staryk/planet.py
staryk/solar.py
staryk/star.py
staryk/util.py
kyeungkap-0.0.2.dist-info/METADATA
kyeungkap-0.0.2.dist-info/WHEEL
kyeungkap-0.0.2.dist-info/top_level.txt
kyeungkap-0.0.2.dist-info/RECORD
