Metadata-Version: 2.1
Name: kyeungkap
Version: 0.0.2
Summary: sample package
Home-page: https://github.com/nicecoding1/
Author: kyeungkap
Author-email: kyeungkap@outlook.com
License: UNKNOWN
Platform: UNKNOWN
Classifier: Programming Language :: Python :: 3
Classifier: License :: OSI Approved :: MIT License
Classifier: Operating System :: OS Independent
Requires-Python: >=3.6
